README.md
setup.py
thumbor_focus_filter/__init__.py
thumbor_focus_filter/focus.py
thumbor_focus_filter.egg-info/PKG-INFO
thumbor_focus_filter.egg-info/SOURCES.txt
thumbor_focus_filter.egg-info/dependency_links.txt
thumbor_focus_filter.egg-info/requires.txt
thumbor_focus_filter.egg-info/top_level.txt